kesi/__init__.py
kesi/butkian/__init__.py
kesi/butkian/ji.py
kesi/butkian/kongiong.py
kesi/butkian/ku.py
kesi/butkian/su.py
kesi/susia/POJ.py
kesi/susia/TL.py
kesi/susia/__init__.py
kesi/susia/kongke.py
kesi/susia/pio.py
KeSi-1.6.0.dist-info/LICENSE
KeSi-1.6.0.dist-info/METADATA
KeSi-1.6.0.dist-info/WHEEL
KeSi-1.6.0.dist-info/top_level.txt
KeSi-1.6.0.dist-info/RECORD
