Metadata-Version: 2.1
Name: KeSi
Version: 1.6.0
Summary: 台語文NLP家私
Home-page: https://ithuan.tw/
Download-URL: https://github.com/i3thuan5/KeSi
Author: Tshuà Bûn-lī
Author-email: ithuan@ithuan.tw
Keywords: Parser,Alignment,Taigi,Hanji,Lomaji
Classifier: Development Status :: 3 - Alpha
Classifier: Operating System :: Unix
Classifier: Programming Language :: Python :: 3.6
Classifier: Programming Language :: Python :: 3.7
Classifier: Topic :: Text Processing
Classifier: Topic :: Text Processing :: Linguistic
License-File: LICENSE
